MANIFEST.in
README.md
setup.py
examples/data/run_ex.log
examples/data/mouse/cov
examples/data/mouse/pheno
examples/data/mouse/pheno2
examples/data/mouse/plink.bed
examples/data/mouse/plink.bim
examples/data/mouse/plink.fam
examples/data/mouse/readme
examples/data/mouse_long/phe.balance.txt
examples/data/mouse_long/phe.unbalance.txt
examples/data/mouse_long/plink.bed
examples/data/mouse_long/plink.bim
examples/data/mouse_long/plink.fam
examples/data/mouse_long/readme
examples/data/yeast/CobaltChloride
examples/data/yeast/CobaltChloride.bed
examples/data/yeast/CobaltChloride.bim
examples/data/yeast/CobaltChloride.fam
examples/data/yeast/CobaltChloride12
examples/data/yeast/CobaltChloride2
examples/data/yeast/CobaltChloride3
examples/data/yeast/chr_code
examples/gmat/cal_agmat.py
examples/gmat/cal_dgmat.py
examples/longwas/balance_test.py
examples/longwas/balance_test2.py
examples/longwas/test.py
examples/longwas/unbalance_test.py
examples/longwas/unbalance_test2.py
examples/mvlmm/fixed.py
examples/mvlmm/var_com.py
examples/remma/remma_add_cpu.py
examples/remma/remma_cpu.py
examples/uvlmm/uvlmm_varcom.py
examples/uvlmm/uvlmm_varcom2.py
examples/uvlmm/gwas/fixed_mouse.py
examples/uvlmm/gwas/fixed_yeast.py
examples/uvlmm/gwas/gmatrix.py
gmat/__init__.py
gmat.egg-info/PKG-INFO
gmat.egg-info/SOURCES.txt
gmat.egg-info/dependency_links.txt
gmat.egg-info/requires.txt
gmat.egg-info/top_level.txt
gmat/bayes/__init__.py
gmat/bayes/bayesA.py
gmat/common/__init__.py
gmat/common/common.py
gmat/common/full_col_rank.py
gmat/common/is_positive.py
gmat/gmatrix/__init__.py
gmat/gmatrix/gmatrix.py
gmat/gmatrix/gmatrix_.py
gmat/gmatrix/pca.py
gmat/longwas/__init__.py
gmat/longwas/common.py
gmat/longwas/balance/__init__.py
gmat/longwas/balance/_common.py
gmat/longwas/balance/_emai.py
gmat/longwas/balance/_pre_data.py
gmat/longwas/balance/balance_longwas_emai.py
gmat/longwas/balance/balance_longwas_fixed.py
gmat/longwas/balance/balance_longwas_fixed_permutation.py
gmat/longwas/balance/balance_longwas_trans.py
gmat/longwas/balance/balance_longwas_trans_permutation.py
gmat/longwas/balance/balance_varcom.py
