Metadata-Version: 1.0
Name: gmat
Version: 2021.6.17
Summary: Genomic Multivariate Analysis Tools
Home-page: https://github.com/chaoning/GMAT
Author: Chao Ning
Author-email: ningchao91@gmail.com
License: UNKNOWN
Platform: all
